{
  "TranslationProperties": {
    "Name": "items.DP_Fan.name"
  },
  "Icon": "Icons/ItemsGenerated/DP_Fan.png",
  "Model": "Items/Tools/DP_Fan/Fan.blockymodel",
  "Texture": "Items/Tools/DP_Fan/Fan_Texture.png",

  "PlayerAnimationsId": "DP_Fan_Animations",

  "MaxDurability": 50,
  "Quality": "Rare",
  "MaxStack": 1,
  "ItemLevel": 3,
  "Categories": [
    "Items.Tools"
  ],
  "Tags": {
    "Type": [
      "Tool"
    ],
    "Family": [
      "Dont Perish"
    ]
  },
  "Interactions": {
    "Secondary": {
      "Interactions": ["Fan_Condition"]
    }
  },
  "IconProperties": {
    "Scale": 0.55,
    "Translation": [ 0, -10 ],
    "Rotation": [ 0, 45, 0 ]
  },
  "Set": "",
  "Scale": 1
}
